scrapy_google_chat.py
scrapy_googlechat-1.1.dist-info/LICENSE.md
scrapy_googlechat-1.1.dist-info/METADATA
scrapy_googlechat-1.1.dist-info/WHEEL
scrapy_googlechat-1.1.dist-info/top_level.txt
scrapy_googlechat-1.1.dist-info/RECORD
