Metadata-Version: 2.1
Name: scrapy-googlechat
Version: 1.1
Summary: Send crawl reports from Scrapy spiders to Google Chat
Home-page: https://github.com/innovinati/scrapy-googlechat
Author: Maximilian Wolf
Author-email: maximilian.wolf@innovinati.com
License: UNKNOWN
Project-URL: Bug Reports, https://github.com/innovinati/scrapy-googlechat/issues
Project-URL: Source, https://github.com/innovinati/scrapy-googlechat/
Keywords: scrapy,google chat,bot
Platform: UNKNOWN
Classifier: Development Status :: 5 - Production/Stable
Classifier: Intended Audience :: Developers
Classifier: Topic :: Internet :: WWW/HTTP
Classifier: License :: OSI Approved :: MIT License
Classifier: Programming Language :: Python :: 3
Classifier: Programming Language :: Python :: 3.5
Classifier: Programming Language :: Python :: 3.6
Classifier: Programming Language :: Python :: 3.7
Classifier: Programming Language :: Python :: 3.8
Classifier: Programming Language :: Python :: 3 :: Only
Requires-Python: >=3.5, <4
Requires-Dist: scrapy
